backend_central_dev/__init__.py
backend_central_dev/performance_metrics.py
backend_central_dev/task_executor.py
backend_central_dev/task_executor_blueprint.py
backend_central_dev/task_func.py
backend_central_dev/task_manager.py
backend_central_dev/task_publisher.py
backend_central_dev/xai_sdk.py
backend_central_dev/constant/Configuration.py
backend_central_dev/constant/ConfigurationType.py
backend_central_dev/constant/ExecutorRegInfo.py
backend_central_dev/constant/ExecutorTicketInfo.py
backend_central_dev/constant/ExecutorType.py
backend_central_dev/constant/Mongo.py
backend_central_dev/constant/PipelineExecution.py
backend_central_dev/constant/PipelineSheet.py
backend_central_dev/constant/PipelineType.py
backend_central_dev/constant/TaskExecution.py
backend_central_dev/constant/TaskSheet.py
backend_central_dev/constant/TaskStatus.py
backend_central_dev/constant/TaskType.py
backend_central_dev/constant/__init__.py
backend_central_dev/data_processing/__init__.py
backend_central_dev/data_processing/dataset_utils.py
backend_central_dev/data_processing/mix/CutMixUp.py
backend_central_dev/data_processing/mix/PuzzleMix.py
backend_central_dev/data_processing/mix/__init__.py
backend_central_dev/data_processing/mix/aug_base.py
backend_central_dev/entity/WsMessage.py
backend_central_dev/entity/__init__.py
backend_central_dev/model_training/__init__.py
backend_central_dev/model_training/lightning_model.py
backend_central_dev/model_training/predict.py
backend_central_dev/model_training/train.py
backend_central_dev/utils/__init__.py
backend_central_dev/utils/azure_blob_helper.py
backend_central_dev/utils/data_utils.py
backend_central_dev/utils/loggers.py
backend_central_dev/utils/module_utils.py
backend_central_dev/utils/mongodb_helper.py
backend_central_dev/utils/plotting_utils.py
backend_central_dev/utils/provenence_utils.py
backend_central_dev/utils/pytorch_utils.py
backend_central_dev/utils/system_utils.py
backend_central_dev/xai/__init__.py
backend_central_dev-0.2.5.dist-info/METADATA
backend_central_dev-0.2.5.dist-info/WHEEL
backend_central_dev-0.2.5.dist-info/top_level.txt
backend_central_dev-0.2.5.dist-info/RECORD
