Metadata-Version: 2.4
Name: backend_central_dev
Version: 0.2.5
Requires-Dist: flask[async]==3.1.0
Requires-Dist: lightning
Requires-Dist: scikit-learn
Requires-Dist: torch
Requires-Dist: torchaudio
Requires-Dist: torchvision
Requires-Dist: numba
Requires-Dist: numpy
Requires-Dist: autopep8
Requires-Dist: pandas
Requires-Dist: pillow
Requires-Dist: opencv-python
Requires-Dist: tqdm
Requires-Dist: tensorboard
Requires-Dist: seaborn
Requires-Dist: scikit-image
Requires-Dist: python-dotenv
Requires-Dist: flask-cors
Requires-Dist: psutil
Requires-Dist: radon
Requires-Dist: requests
Requires-Dist: pyyaml
Requires-Dist: matplotlib
Requires-Dist: jupyter
Requires-Dist: notebook
Requires-Dist: tinydb
Requires-Dist: pymongo
Requires-Dist: codecarbon
Requires-Dist: expiringdict
Requires-Dist: prov
Requires-Dist: geffnet
Requires-Dist: torch-uncertainty
Requires-Dist: websockets
Requires-Dist: tabulate
Requires-Dist: shap
Requires-Dist: lime
Requires-Dist: kaggle==1.5.14
Requires-Dist: grad-cam
Requires-Dist: gco-wrapper
Requires-Dist: flask-socketio
Requires-Dist: eventlet
Requires-Dist: python-socketio
Requires-Dist: gunicorn
Dynamic: requires-dist
